pywharf_bundles/__init__.py
pywharf-0.2.3.dist-info/entry_points.txt
pywharf-0.2.3.dist-info/LICENSE
pywharf-0.2.3.dist-info/WHEEL
pywharf-0.2.3.dist-info/METADATA
pywharf-0.2.3.dist-info/RECORD
