Metadata-Version: 2.1
Name: pywharf
Version: 0.2.3
Summary: A private PyPI server powered by flexible backends.
Home-page: https://github.com/pywharf/pywharf
License: MIT
Keywords: private,pypi,packaging,dependency
Author: huntzhan
Author-email: huntzhan.dev@gmail.com
Requires-Python: >=3.7,<4.0
Classifier: License :: OSI Approved :: MIT License
Classifier: Programming Language :: Python :: 3
Classifier: Programming Language :: Python :: 3.7
Classifier: Programming Language :: Python :: 3.8
Classifier: Topic :: Software Development :: Build Tools
Classifier: Topic :: Software Development :: Libraries :: Python Modules
Requires-Dist: pywharf-core (==0.2.2)
Requires-Dist: pywharf-github (==0.2.0)
Project-URL: Repository, https://github.com/pywharf/pywharf
